jasmcaer/__init__.py
jasmcaer/model.py
jasmcaer/preprocess.py
jasmcaer/utils.py
jasmcaer-0.0.9.dist-info/LICENSE
jasmcaer-0.0.9.dist-info/METADATA
jasmcaer-0.0.9.dist-info/WHEEL
jasmcaer-0.0.9.dist-info/top_level.txt
jasmcaer-0.0.9.dist-info/RECORD
