Metadata-Version: 2.1
Name: jasmcaer
Version: 0.0.9
Summary: A Computer Vision library in Python with powerful image processing operations, including support for Deep Learning models built using the Keras framework
Home-page: https://github.com/jasmcaus/caer
Author: Jason Dsouza
Author-email: jasmcaus@gmail.com
License: MIT
Keywords: computer vision,deep learning,image processing,opencv,matplotlib
Platform: UNKNOWN
Classifier: Development Status :: 3 - Alpha
Classifier: Intended Audience :: Developers
Classifier: Intended Audience :: Education
Classifier: Intended Audience :: Science/Research
Classifier: Programming Language :: Python :: 3
Classifier: Programming Language :: Python :: 3 :: Only
Classifier: Programming Language :: Python :: 3.5
Classifier: Programming Language :: Python :: 3.6
Classifier: Programming Language :: Python :: 3.7
Classifier: Programming Language :: Python :: 3.8
Classifier: Operating System :: MacOS
Classifier: Operating System :: Microsoft :: Windows
Classifier: License :: OSI Approved :: MIT License
Requires-Dist: numpy
Requires-Dist: opencv-contrib-python
